{
    "ema_spread_scaled": 0.8515449719524186,
    "mcclenllan_scaled": 0.45217745019219147,
    "p_c_ema_scaled": 0.0,
    "vix_ema_spread_scaled": 0.0,
    "safe_spread_scaled": 0.2631730419783368,
    "junk_spread_scaled": 0.7287553648068672,
    "stock_strength_scaled": 0.1973065181466193,
    "ema_spread_imputed": 0,
    "mcclenllan_imputed": 0,
    "p_c_ema_imputed": 0,
    "vix_ema_spread_imputed": 0,
    "safe_spread_imputed": 0,
    "junk_spread_imputed": 0,
    "stock_strength_imputed": 0,
    "imputed_count": 0
}