{
    "data": [
        {
            "x": "2022-08-26",
            "y": 2483.03,
            "z": 46.92635822886456
        },
        {
            "x": "2022-08-29",
            "y": 2428.89,
            "z": 45.12741757993341
        },
        {
            "x": "2022-08-30",
            "y": 2452.93,
            "z": 44.37360559537686
        },
        {
            "x": "2022-08-31",
            "y": 2474.05,
            "z": 43.493230404740686
        },
        {
            "x": "2022-09-01",
            "y": 2417.61,
            "z": 41.50365408023943
        },
        {
            "x": "2022-09-02",
            "y": 2411.41,
            "z": 39.84017902538663
        },
        {
            "x": "2022-09-05",
            "y": 2405.68,
            "z": 39.29243993718078
        },
        {
            "x": "2022-09-06",
            "y": 2412.02,
            "z": 37.855903482664125
        },
        {
            "x": "2022-09-07",
            "y": 2378.46,
            "z": 35.830439196337444
        },
        {
            "x": "2022-09-08",
            "y": 2386.28,
            "z": 34.84434946962523
        },
        {
            "x": "2022-09-13",
            "y": 2451.54,
            "z": 34.52704322775817
        },
        {
            "x": "2022-09-14",
            "y": 2413.42,
            "z": 33.74271293720191
        },
        {
            "x": "2022-09-15",
            "y": 2403.83,
            "z": 33.08148822395677
        },
        {
            "x": "2022-09-16",
            "y": 2384.78,
            "z": 32.995859673978046
        },
        {
            "x": "2022-09-19",
            "y": 2357.66,
            "z": 32.34129312678946
        },
        {
            "x": "2022-09-20",
            "y": 2369.85,
            "z": 32.090175591476
        },
        {
            "x": "2022-09-21",
            "y": 2349.21,
            "z": 32.59001012978596
        },
        {
            "x": "2022-09-22",
            "y": 2334.31,
            "z": 32.87726058224964
        },
        {
            "x": "2022-09-23",
            "y": 2292.0,
            "z": 32.41435813252342
        },
        {
            "x": "2022-09-26",
            "y": 2222.94,
            "z": 30.59498403478018
        },
        {
            "x": "2022-09-27",
            "y": 2225.86,
            "z": 28.634044384251162
        },
        {
            "x": "2022-09-28",
            "y": 2171.29,
            "z": 25.239679159717696
        },
        {
            "x": "2022-09-29",
            "y": 2172.93,
            "z": 21.934948555571793
        },
        {
            "x": "2022-09-30",
            "y": 2157.49,
            "z": 19.56191018609054
        },
        {
            "x": "2022-10-04",
            "y": 2211.38,
            "z": 20.23079772000473
        },
        {
            "x": "2022-10-05",
            "y": 2217.22,
            "z": 20.07970263443904
        },
        {
            "x": "2022-10-06",
            "y": 2239.86,
            "z": 22.155732838623017
        },
        {
            "x": "2022-10-07",
            "y": 2234.84,
            "z": 24.55478032239546
        },
        {
            "x": "2022-10-11",
            "y": 2194.07,
            "z": 25.93285362749731
        },
        {
            "x": "2022-10-12",
            "y": 2204.47,
            "z": 26.118914814471765
        },
        {
            "x": "2022-10-13",
            "y": 2164.87,
            "z": 26.275535533699234
        },
        {
            "x": "2022-10-14",
            "y": 2214.55,
            "z": 27.02594628563361
        },
        {
            "x": "2022-10-17",
            "y": 2221.71,
            "z": 27.59840379432809
        },
        {
            "x": "2022-10-18",
            "y": 2251.95,
            "z": 29.740925030049333
        },
        {
            "x": "2022-10-19",
            "y": 2239.44,
            "z": 31.328113779480425
        },
        {
            "x": "2022-10-20",
            "y": 2220.09,
            "z": 32.37898504024937
        },
        {
            "x": "2022-10-21",
            "y": 2215.12,
            "z": 32.10269356949716
        },
        {
            "x": "2022-10-24",
            "y": 2238.16,
            "z": 32.21216069418731
        },
        {
            "x": "2022-10-25",
            "y": 2237.07,
            "z": 32.31192514684731
        },
        {
            "x": "2022-10-26",
            "y": 2251.56,
            "z": 33.352385692536835
        },
        {
            "x": "2022-10-27",
            "y": 2290.78,
            "z": 36.1227411583328
        },
        {
            "x": "2022-10-28",
            "y": 2270.4,
            "z": 38.690169620525694
        },
        {
            "x": "2022-10-31",
            "y": 2295.61,
            "z": 41.61140965894615
        },
        {
            "x": "2022-11-01",
            "y": 2337.22,
            "z": 44.205738335941575
        },
        {
            "x": "2022-11-02",
            "y": 2338.87,
            "z": 46.3260052653777
        },
        {
            "x": "2022-11-03",
            "y": 2331.17,
            "z": 46.986713210204115
        },
        {
            "x": "2022-11-04",
            "y": 2350.43,
            "z": 48.18240024869204
        },
        {
            "x": "2022-11-07",
            "y": 2373.79,
            "z": 49.37636988250527
        },
        {
            "x": "2022-11-08",
            "y": 2401.04,
            "z": 51.13222836565798
        },
        {
            "x": "2022-11-09",
            "y": 2426.41,
            "z": 53.208400405886756
        },
        {
            "x": "2022-11-10",
            "y": 2404.23,
            "z": 55.45787230759284
        },
        {
            "x": "2022-11-11",
            "y": 2485.16,
            "z": 57.75450593187136
        },
        {
            "x": "2022-11-14",
            "y": 2476.65,
            "z": 58.620576890645964
        },
        {
            "x": "2022-11-15",
            "y": 2482.33,
            "z": 58.45209443103904
        },
        {
            "x": "2022-11-16",
            "y": 2479.45,
            "z": 57.952286847666265
        },
        {
            "x": "2022-11-17",
            "y": 2444.9,
            "z": 57.315032321288
        },
        {
            "x": "2022-11-18",
            "y": 2446.48,
            "z": 56.05006884971696
        },
        {
            "x": "2022-11-21",
            "y": 2421.5,
            "z": 54.943962089461536
        },
        {
            "x": "2022-12-05",
            "y": 2421.32,
            "z": 52.7511381071414
        },
        {
            "x": "2022-12-06",
            "y": 2395.16,
            "z": 50.30556376591409
        },
        {
            "x": "2022-12-07",
            "y": 2384.81,
            "z": 48.21227091481946
        },
        {
            "x": "2022-12-08",
            "y": 2373.08,
            "z": 45.998834412275876
        },
        {
            "x": "2022-12-09",
            "y": 2391.04,
            "z": 44.09394507446544
        },
        {
            "x": "2022-12-12",
            "y": 2375.02,
            "z": 42.967023852222724
        },
        {
            "x": "2022-12-13",
            "y": 2374.4,
            "z": 41.83191517187419
        },
        {
            "x": "2022-12-14",
            "y": 2401.25,
            "z": 41.37523917546997
        },
        {
            "x": "2022-12-15",
            "y": 2362.97,
            "z": 41.13097909175083
        },
        {
            "x": "2022-12-16",
            "y": 2362.02,
            "z": 41.16480663778581
        },
        {
            "x": "2022-12-19",
            "y": 2354.17,
            "z": 41.553276859878395
        },
        {
            "x": "2022-12-20",
            "y": 2335.29,
            "z": 41.215885542276986
        },
        {
            "x": "2022-12-21",
            "y": 2330.95,
            "z": 40.19391788415911
        },
        {
            "x": "2022-12-22",
            "y": 2358.73,
            "z": 39.0980251139453
        },
        {
            "x": "2022-12-23",
            "y": 2315.69,
            "z": 37.2378423328572
        },
        {
            "x": "2022-12-26",
            "y": 2319.14,
            "z": 35.43778892581045
        },
        {
            "x": "2022-12-27",
            "y": 2334.79,
            "z": 34.626809133024246
        },
        {
            "x": "2022-12-28",
            "y": 2282.45,
            "z": 32.91001105804784
        },
        {
            "x": "2022-12-29",
            "y": 2238.4,
            "z": 30.86226878479841
        },
        {
            "x": "2023-01-02",
            "y": 2227.67,
            "z": 29.96183408833026
        },
        {
            "x": "2023-01-03",
            "y": 2220.68,
            "z": 29.22708140069812
        },
        {
            "x": "2023-01-04",
            "y": 2257.98,
            "z": 29.502787778636844
        },
        {
            "x": "2023-01-05",
            "y": 2266.65,
            "z": 31.16078550356267
        },
        {
            "x": "2023-01-06",
            "y": 2291.97,
            "z": 34.05998920612508
        },
        {
            "x": "2023-01-09",
            "y": 2352.19,
            "z": 37.42460697836263
        },
        {
            "x": "2023-01-10",
            "y": 2353.31,
            "z": 41.29768725157586
        },
        {
            "x": "2023-01-11",
            "y": 2361.53,
            "z": 44.098962713628495
        },
        {
            "x": "2023-01-12",
            "y": 2367.1,
            "z": 46.45939940405761
        },
        {
            "x": "2023-01-13",
            "y": 2388.09,
            "z": 48.77864785292493
        },
        {
            "x": "2023-01-16",
            "y": 2401.86,
            "z": 50.01063334125265
        },
        {
            "x": "2023-01-17",
            "y": 2381.39,
            "z": 50.37454849052385
        },
        {
            "x": "2023-01-18",
            "y": 2370.32,
            "z": 50.77949384294364
        },
        {
            "x": "2023-01-19",
            "y": 2382.34,
            "z": 51.27616419599491
        },
        {
            "x": "2023-01-20",
            "y": 2397.26,
            "z": 51.48267783776074
        },
        {
            "x": "2023-01-25",
            "y": 2430.57,
            "z": 52.121731853462606
        },
        {
            "x": "2023-01-26",
            "y": 2470.65,
            "z": 53.38260816673321
        },
        {
            "x": "2023-01-27",
            "y": 2486.02,
            "z": 55.4804510318332
        },
        {
            "x": "2023-01-30",
            "y": 2452.47,
            "z": 57.97389266591334
        },
        {
            "x": "2023-01-31",
            "y": 2427.08,
            "z": 60.332131961841036
        },
        {
            "x": "2023-02-01",
            "y": 2451.8,
            "z": 63.03160034097152
        },
        {
            "x": "2023-02-02",
            "y": 2470.88,
            "z": 65.62711853568439
        },
        {
            "x": "2023-02-03",
            "y": 2482.4,
            "z": 66.95350724807466
        },
        {
            "x": "2023-02-06",
            "y": 2440.19,
            "z": 67.17076716555603
        },
        {
            "x": "2023-02-07",
            "y": 2453.71,
            "z": 66.69088095747182
        },
        {
            "x": "2023-02-08",
            "y": 2485.64,
            "z": 65.70151751510551
        },
        {
            "x": "2023-02-09",
            "y": 2483.52,
            "z": 64.24924677225228
        },
        {
            "x": "2023-02-10",
            "y": 2471.73,
            "z": 62.78325848576041
        },
        {
            "x": "2023-02-13",
            "y": 2454.7,
            "z": 61.299512146391486
        },
        {
            "x": "2023-02-14",
            "y": 2467.64,
            "z": 60.07703337759108
        },
        {
            "x": "2023-02-15",
            "y": 2429.9,
            "z": 58.38372195739637
        },
        {
            "x": "2023-02-16",
            "y": 2477.48,
            "z": 57.60688940928105
        },
        {
            "x": "2023-02-17",
            "y": 2453.21,
            "z": 57.19041689131927
        },
        {
            "x": "2023-02-20",
            "y": 2457.12,
            "z": 57.60010790843014
        },
        {
            "x": "2023-02-21",
            "y": 2460.96,
            "z": 57.658193800099525
        },
        {
            "x": "2023-02-22",
            "y": 2419.68,
            "z": 56.80603586977109
        },
        {
            "x": "2023-02-23",
            "y": 2441.09,
            "z": 55.154075630433226
        },
        {
            "x": "2023-02-24",
            "y": 2425.61,
            "z": 53.51464981442227
        },
        {
            "x": "2023-02-27",
            "y": 2404.64,
            "z": 51.169119525369865
        },
        {
            "x": "2023-02-28",
            "y": 2414.85,
            "z": 49.578482359282695
        },
        {
            "x": "2023-03-02",
            "y": 2429.85,
            "z": 49.01653536105163
        },
        {
            "x": "2023-03-03",
            "y": 2434.07,
            "z": 48.58178340234398
        },
        {
            "x": "2023-03-06",
            "y": 2464.62,
            "z": 48.529448495454076
        },
        {
            "x": "2023-03-07",
            "y": 2465.35,
            "z": 49.57092416828165
        },
        {
            "x": "2023-03-08",
            "y": 2433.91,
            "z": 49.81195594550325
        },
        {
            "x": "2023-03-09",
            "y": 2421.09,
            "z": 50.178366863350654
        },
        {
            "x": "2023-03-10",
            "y": 2396.59,
            "z": 50.10778917162382
        },
        {
            "x": "2023-03-13",
            "y": 2412.6,
            "z": 49.53893734529554
        },
        {
            "x": "2023-03-14",
            "y": 2350.97,
            "z": 47.030497585306165
        },
        {
            "x": "2023-03-15",
            "y": 2381.72,
            "z": 45.99964987589351
        },
        {
            "x": "2023-03-16",
            "y": 2379.91,
            "z": 44.364723591394345
        },
        {
            "x": "2023-03-17",
            "y": 2397.69,
            "z": 43.32562313316875
        },
        {
            "x": "2023-03-20",
            "y": 2381.2,
            "z": 41.97584782883522
        },
        {
            "x": "2023-03-21",
            "y": 2390.35,
            "z": 42.42400665212888
        },
        {
            "x": "2023-03-22",
            "y": 2418.96,
            "z": 42.434718186053814
        },
        {
            "x": "2023-03-23",
            "y": 2426.48,
            "z": 43.177384342824844
        },
        {
            "x": "2023-03-24",
            "y": 2416.96,
            "z": 43.82477673280778
        },
        {
            "x": "2023-03-27",
            "y": 2411.22,
            "z": 45.183008167958505
        },
        {
            "x": "2023-03-28",
            "y": 2436.94,
            "z": 46.41326669290611
        },
        {
            "x": "2023-03-29",
            "y": 2445.92,
            "z": 47.10947969424374
        },
        {
            "x": "2023-03-30",
            "y": 2455.16,
            "z": 48.135781460604925
        },
        {
            "x": "2023-03-31",
            "y": 2478.86,
            "z": 49.07644954112612
        },
        {
            "x": "2023-04-03",
            "y": 2474.34,
            "z": 49.34950223002568
        },
        {
            "x": "2023-04-04",
            "y": 2482.51,
            "z": 49.99818336506873
        },
        {
            "x": "2023-04-05",
            "y": 2497.21,
            "z": 51.135153330784796
        },
        {
            "x": "2023-04-06",
            "y": 2461.23,
            "z": 51.85037551773534
        },
        {
            "x": "2023-04-07",
            "y": 2492.41,
            "z": 53.22931535700538
        },
        {
            "x": "2023-04-10",
            "y": 2514.08,
            "z": 55.72231716852914
        },
        {
            "x": "2023-04-11",
            "y": 2549.86,
            "z": 58.40267996419218
        },
        {
            "x": "2023-04-12",
            "y": 2552.64,
            "z": 60.953870380515355
        },
        {
            "x": "2023-04-13",
            "y": 2563.66,
            "z": 63.56074169927324
        },
        {
            "x": "2023-04-14",
            "y": 2573.49,
            "z": 65.31524761541942
        },
        {
            "x": "2023-04-17",
            "y": 2577.91,
            "z": 66.62705958860626
        }
    ]
}