{
    "data": [
        {
            "x": "2022-04-06",
            "y": 2737.03,
            "z": 48.469017851912966
        },
        {
            "x": "2022-04-07",
            "y": 2697.86,
            "z": 48.3898684637706
        },
        {
            "x": "2022-04-08",
            "y": 2702.39,
            "z": 49.29999635270195
        },
        {
            "x": "2022-04-11",
            "y": 2695.1,
            "z": 49.370643219043025
        },
        {
            "x": "2022-04-12",
            "y": 2668.76,
            "z": 48.342979742155656
        },
        {
            "x": "2022-04-13",
            "y": 2718.49,
            "z": 48.272423389015316
        },
        {
            "x": "2022-04-14",
            "y": 2718.71,
            "z": 48.94499528073711
        },
        {
            "x": "2022-04-15",
            "y": 2698.06,
            "z": 48.521188965916046
        },
        {
            "x": "2022-04-18",
            "y": 2695.21,
            "z": 48.19305392196329
        },
        {
            "x": "2022-04-19",
            "y": 2720.89,
            "z": 48.972355789826196
        },
        {
            "x": "2022-04-20",
            "y": 2720.69,
            "z": 49.23236455360374
        },
        {
            "x": "2022-04-21",
            "y": 2730.21,
            "z": 49.64057470213375
        },
        {
            "x": "2022-04-22",
            "y": 2706.71,
            "z": 50.0503184772899
        },
        {
            "x": "2022-04-25",
            "y": 2659.13,
            "z": 48.98262857785983
        },
        {
            "x": "2022-04-26",
            "y": 2670.31,
            "z": 47.71475658699734
        },
        {
            "x": "2022-04-27",
            "y": 2641.06,
            "z": 45.81645922173392
        },
        {
            "x": "2022-04-28",
            "y": 2669.49,
            "z": 44.26857283308415
        },
        {
            "x": "2022-04-29",
            "y": 2697.05,
            "z": 43.54459139098981
        },
        {
            "x": "2022-05-02",
            "y": 2689.45,
            "z": 43.3010865158138
        },
        {
            "x": "2022-05-03",
            "y": 2682.46,
            "z": 42.72288205140152
        },
        {
            "x": "2022-05-04",
            "y": 2679.57,
            "z": 43.23857861851674
        },
        {
            "x": "2022-05-06",
            "y": 2646.51,
            "z": 42.61579877639754
        },
        {
            "x": "2022-05-09",
            "y": 2612.81,
            "z": 40.71655744698828
        },
        {
            "x": "2022-05-10",
            "y": 2598.56,
            "z": 39.83080966897876
        },
        {
            "x": "2022-05-11",
            "y": 2594.27,
            "z": 39.10266374041812
        },
        {
            "x": "2022-05-12",
            "y": 2552.08,
            "z": 37.00366477865312
        },
        {
            "x": "2022-05-13",
            "y": 2606.24,
            "z": 36.65085838386984
        },
        {
            "x": "2022-05-16",
            "y": 2598.58,
            "z": 37.05809824915612
        },
        {
            "x": "2022-05-17",
            "y": 2622.44,
            "z": 37.49598724853685
        },
        {
            "x": "2022-05-18",
            "y": 2627.98,
            "z": 37.332358822831836
        },
        {
            "x": "2022-05-19",
            "y": 2594.34,
            "z": 37.710461472137226
        },
        {
            "x": "2022-05-20",
            "y": 2641.29,
            "z": 37.43973839071754
        },
        {
            "x": "2022-05-23",
            "y": 2649.38,
            "z": 37.70679585294421
        },
        {
            "x": "2022-05-24",
            "y": 2607.87,
            "z": 37.071255680192856
        },
        {
            "x": "2022-05-25",
            "y": 2619.22,
            "z": 37.76400673042308
        },
        {
            "x": "2022-05-26",
            "y": 2614.45,
            "z": 39.178732706170024
        },
        {
            "x": "2022-05-27",
            "y": 2640.05,
            "z": 39.68744148346828
        },
        {
            "x": "2022-05-30",
            "y": 2671.66,
            "z": 39.792012477262475
        },
        {
            "x": "2022-05-31",
            "y": 2687.9,
            "z": 40.50488314070291
        },
        {
            "x": "2022-06-02",
            "y": 2660.99,
            "z": 39.80048027293991
        },
        {
            "x": "2022-06-03",
            "y": 2672.65,
            "z": 39.01823010258157
        },
        {
            "x": "2022-06-07",
            "y": 2628.34,
            "z": 38.52066830525702
        },
        {
            "x": "2022-06-08",
            "y": 2628.15,
            "z": 39.02298059179674
        },
        {
            "x": "2022-06-09",
            "y": 2627.44,
            "z": 39.75097999814955
        },
        {
            "x": "2022-06-10",
            "y": 2597.87,
            "z": 41.854195990023825
        },
        {
            "x": "2022-06-13",
            "y": 2506.51,
            "z": 42.09738376319645
        },
        {
            "x": "2022-06-14",
            "y": 2494.97,
            "z": 41.51610233737134
        },
        {
            "x": "2022-06-15",
            "y": 2449.38,
            "z": 38.94850533947335
        },
        {
            "x": "2022-06-16",
            "y": 2453.41,
            "z": 36.40458566850283
        },
        {
            "x": "2022-06-17",
            "y": 2442.93,
            "z": 32.79662855709661
        },
        {
            "x": "2022-06-20",
            "y": 2393.03,
            "z": 30.30560816219579
        },
        {
            "x": "2022-06-21",
            "y": 2410.93,
            "z": 29.214872799356716
        },
        {
            "x": "2022-06-22",
            "y": 2344.81,
            "z": 28.283768867314603
        },
        {
            "x": "2022-06-23",
            "y": 2316.32,
            "z": 26.813558717242756
        },
        {
            "x": "2022-06-24",
            "y": 2368.6,
            "z": 26.737687869473255
        },
        {
            "x": "2022-06-27",
            "y": 2403.92,
            "z": 28.011953013872528
        },
        {
            "x": "2022-06-28",
            "y": 2424.09,
            "z": 28.66782404341426
        },
        {
            "x": "2022-06-29",
            "y": 2379.99,
            "z": 29.54627052510665
        },
        {
            "x": "2022-06-30",
            "y": 2334.64,
            "z": 30.523950889691008
        },
        {
            "x": "2022-07-01",
            "y": 2307.42,
            "z": 30.160337151471246
        },
        {
            "x": "2022-07-04",
            "y": 2302.34,
            "z": 29.223825842912436
        },
        {
            "x": "2022-07-05",
            "y": 2343.78,
            "z": 29.175888820133288
        },
        {
            "x": "2022-07-06",
            "y": 2294.01,
            "z": 29.28263342013681
        },
        {
            "x": "2022-07-07",
            "y": 2336.27,
            "z": 30.494471097020046
        },
        {
            "x": "2022-07-08",
            "y": 2352.61,
            "z": 32.64207358054444
        },
        {
            "x": "2022-07-11",
            "y": 2342.27,
            "z": 35.290357356269375
        },
        {
            "x": "2022-07-12",
            "y": 2319.76,
            "z": 37.24921349135715
        },
        {
            "x": "2022-07-13",
            "y": 2330.61,
            "z": 39.73273729098531
        },
        {
            "x": "2022-07-14",
            "y": 2324.32,
            "z": 41.2162035120517
        },
        {
            "x": "2022-07-15",
            "y": 2332.98,
            "z": 42.31348512972489
        },
        {
            "x": "2022-07-18",
            "y": 2377.25,
            "z": 43.45927295445544
        },
        {
            "x": "2022-07-19",
            "y": 2372.97,
            "z": 44.34446903184487
        },
        {
            "x": "2022-07-20",
            "y": 2388.85,
            "z": 45.86044563202604
        },
        {
            "x": "2022-07-21",
            "y": 2411.16,
            "z": 47.620530459929334
        },
        {
            "x": "2022-07-22",
            "y": 2395.14,
            "z": 48.214391632236186
        },
        {
            "x": "2022-07-25",
            "y": 2405.69,
            "z": 48.11293656154196
        },
        {
            "x": "2022-07-26",
            "y": 2414.96,
            "z": 48.550910244941676
        },
        {
            "x": "2022-07-27",
            "y": 2417.53,
            "z": 48.44356352683282
        },
        {
            "x": "2022-07-28",
            "y": 2437.27,
            "z": 48.63871410716181
        },
        {
            "x": "2022-07-29",
            "y": 2453.5,
            "z": 49.8099975959805
        },
        {
            "x": "2022-08-01",
            "y": 2454.25,
            "z": 50.81451853205661
        },
        {
            "x": "2022-08-02",
            "y": 2441.62,
            "z": 50.844664161348064
        },
        {
            "x": "2022-08-03",
            "y": 2463.45,
            "z": 51.269094994938044
        },
        {
            "x": "2022-08-04",
            "y": 2475.11,
            "z": 50.959582987399486
        },
        {
            "x": "2022-08-05",
            "y": 2492.8,
            "z": 50.729719534737775
        },
        {
            "x": "2022-08-08",
            "y": 2495.1,
            "z": 50.65292076023671
        },
        {
            "x": "2022-08-09",
            "y": 2505.46,
            "z": 51.48832535062661
        },
        {
            "x": "2022-08-10",
            "y": 2482.88,
            "z": 51.396773974422146
        },
        {
            "x": "2022-08-11",
            "y": 2525.78,
            "z": 52.89491578397472
        },
        {
            "x": "2022-08-12",
            "y": 2529.94,
            "z": 53.547470946749094
        },
        {
            "x": "2022-08-16",
            "y": 2535.52,
            "z": 54.17102249168863
        },
        {
            "x": "2022-08-17",
            "y": 2518.47,
            "z": 53.65632831889809
        },
        {
            "x": "2022-08-18",
            "y": 2510.05,
            "z": 52.76648494000968
        },
        {
            "x": "2022-08-19",
            "y": 2494.69,
            "z": 50.55511600024532
        },
        {
            "x": "2022-08-22",
            "y": 2464.5,
            "z": 49.25246908329624
        },
        {
            "x": "2022-08-23",
            "y": 2437.34,
            "z": 47.791890528663686
        },
        {
            "x": "2022-08-24",
            "y": 2449.45,
            "z": 47.21102254494561
        },
        {
            "x": "2022-08-25",
            "y": 2479.26,
            "z": 47.59007195867897
        },
        {
            "x": "2022-08-26",
            "y": 2483.03,
            "z": 47.38842041804571
        },
        {
            "x": "2022-08-29",
            "y": 2428.89,
            "z": 45.61980522975596
        },
        {
            "x": "2022-08-30",
            "y": 2452.93,
            "z": 44.86132705241311
        },
        {
            "x": "2022-08-31",
            "y": 2474.05,
            "z": 43.97076138103324
        },
        {
            "x": "2022-09-01",
            "y": 2417.61,
            "z": 42.02350576286476
        },
        {
            "x": "2022-09-02",
            "y": 2411.41,
            "z": 40.40887540654287
        },
        {
            "x": "2022-09-05",
            "y": 2405.68,
            "z": 39.8849093938275
        },
        {
            "x": "2022-09-06",
            "y": 2412.02,
            "z": 38.48138547118472
        },
        {
            "x": "2022-09-07",
            "y": 2378.46,
            "z": 36.51372827008542
        },
        {
            "x": "2022-09-08",
            "y": 2386.28,
            "z": 35.550966460967366
        },
        {
            "x": "2022-09-13",
            "y": 2451.54,
            "z": 35.21870895510658
        },
        {
            "x": "2022-09-14",
            "y": 2413.42,
            "z": 34.42732520536519
        },
        {
            "x": "2022-09-15",
            "y": 2403.83,
            "z": 33.76706337581207
        },
        {
            "x": "2022-09-16",
            "y": 2384.78,
            "z": 33.67093269823807
        },
        {
            "x": "2022-09-19",
            "y": 2357.66,
            "z": 33.012568280086114
        },
        {
            "x": "2022-09-20",
            "y": 2369.85,
            "z": 32.784362789193
        },
        {
            "x": "2022-09-21",
            "y": 2349.21,
            "z": 33.3068505408092
        },
        {
            "x": "2022-09-22",
            "y": 2334.31,
            "z": 33.61305192259066
        },
        {
            "x": "2022-09-23",
            "y": 2292.0,
            "z": 33.18004674161304
        },
        {
            "x": "2022-09-26",
            "y": 2222.94,
            "z": 31.423926792424616
        },
        {
            "x": "2022-09-27",
            "y": 2225.86,
            "z": 29.53324286587199
        },
        {
            "x": "2022-09-28",
            "y": 2171.29,
            "z": 26.215302837257873
        },
        {
            "x": "2022-09-29",
            "y": 2172.93,
            "z": 22.99054368082572
        },
        {
            "x": "2022-09-30",
            "y": 2157.49,
            "z": 20.628437134910445
        },
        {
            "x": "2022-10-04",
            "y": 2211.38,
            "z": 21.30292452903886
        },
        {
            "x": "2022-10-05",
            "y": 2217.22,
            "z": 21.142377152951216
        },
        {
            "x": "2022-10-06",
            "y": 2239.86,
            "z": 23.177876913942452
        },
        {
            "x": "2022-10-07",
            "y": 2234.84,
            "z": 25.53740320167944
        },
        {
            "x": "2022-10-11",
            "y": 2194.07,
            "z": 26.948757058669326
        },
        {
            "x": "2022-10-12",
            "y": 2204.47,
            "z": 27.128808777413116
        },
        {
            "x": "2022-10-13",
            "y": 2164.87,
            "z": 27.29137765765779
        },
        {
            "x": "2022-10-14",
            "y": 2214.55,
            "z": 28.064437568889552
        },
        {
            "x": "2022-10-17",
            "y": 2221.71,
            "z": 28.654295848560785
        },
        {
            "x": "2022-10-18",
            "y": 2251.95,
            "z": 30.770809144166755
        },
        {
            "x": "2022-10-19",
            "y": 2239.44,
            "z": 32.33584086884218
        },
        {
            "x": "2022-10-20",
            "y": 2220.09,
            "z": 33.375352384418285
        },
        {
            "x": "2022-10-21",
            "y": 2215.12,
            "z": 33.091113095967344
        },
        {
            "x": "2022-10-24",
            "y": 2238.16,
            "z": 33.17953209112339
        },
        {
            "x": "2022-10-25",
            "y": 2237.07,
            "z": 33.26701324181573
        },
        {
            "x": "2022-10-26",
            "y": 2251.56,
            "z": 34.27511354540851
        },
        {
            "x": "2022-10-27",
            "y": 2290.78,
            "z": 36.98314500950664
        },
        {
            "x": "2022-10-28",
            "y": 2270.4,
            "z": 39.47302560591605
        },
        {
            "x": "2022-10-31",
            "y": 2295.61,
            "z": 42.32247062634236
        },
        {
            "x": "2022-11-01",
            "y": 2337.22,
            "z": 44.84488053295699
        },
        {
            "x": "2022-11-02",
            "y": 2338.87,
            "z": 46.92710255111756
        },
        {
            "x": "2022-11-03",
            "y": 2331.17,
            "z": 47.57860936456774
        },
        {
            "x": "2022-11-04",
            "y": 2350.43,
            "z": 48.768089891469835
        },
        {
            "x": "2022-11-07",
            "y": 2373.79,
            "z": 49.95874279806101
        },
        {
            "x": "2022-11-08",
            "y": 2401.04,
            "z": 51.70710055495634
        },
        {
            "x": "2022-11-09",
            "y": 2426.41,
            "z": 53.7542819654102
        },
        {
            "x": "2022-11-10",
            "y": 2404.23,
            "z": 55.97107093340054
        },
        {
            "x": "2022-11-11",
            "y": 2485.16,
            "z": 58.21604687577386
        },
        {
            "x": "2022-11-14",
            "y": 2476.65,
            "z": 59.042439316055734
        },
        {
            "x": "2022-11-15",
            "y": 2482.33,
            "z": 58.85027580825264
        },
        {
            "x": "2022-11-16",
            "y": 2479.45,
            "z": 58.32813531134151
        },
        {
            "x": "2022-11-17",
            "y": 2444.9,
            "z": 57.662833631110615
        },
        {
            "x": "2022-11-18",
            "y": 2446.48,
            "z": 56.391782871574335
        },
        {
            "x": "2022-11-21",
            "y": 2421.5,
            "z": 55.28788094981386
        },
        {
            "x": "2022-12-05",
            "y": 2421.32,
            "z": 53.1168013958536
        },
        {
            "x": "2022-12-06",
            "y": 2395.16,
            "z": 50.72595193741735
        },
        {
            "x": "2022-12-07",
            "y": 2384.81,
            "z": 48.70231132450232
        },
        {
            "x": "2022-12-08",
            "y": 2373.08,
            "z": 46.55928320389431
        },
        {
            "x": "2022-12-09",
            "y": 2391.04,
            "z": 44.71099847084791
        },
        {
            "x": "2022-12-12",
            "y": 2375.02,
            "z": 43.62876387471001
        },
        {
            "x": "2022-12-13",
            "y": 2374.4,
            "z": 42.51802576002612
        },
        {
            "x": "2022-12-14",
            "y": 2401.25,
            "z": 42.04906438578941
        },
        {
            "x": "2022-12-15",
            "y": 2362.97,
            "z": 41.79802035978772
        },
        {
            "x": "2022-12-16",
            "y": 2362.02,
            "z": 41.825212098368965
        },
        {
            "x": "2022-12-19",
            "y": 2354.17,
            "z": 42.20548190558496
        },
        {
            "x": "2022-12-20",
            "y": 2335.29,
            "z": 41.858752261272386
        },
        {
            "x": "2022-12-21",
            "y": 2330.95,
            "z": 40.85246999738318
        },
        {
            "x": "2022-12-22",
            "y": 2358.73,
            "z": 39.747432818894
        },
        {
            "x": "2022-12-23",
            "y": 2315.69,
            "z": 37.88759156000533
        },
        {
            "x": "2022-12-26",
            "y": 2319.14,
            "z": 36.08089619357709
        },
        {
            "x": "2022-12-27",
            "y": 2334.79,
            "z": 35.260214639962946
        },
        {
            "x": "2022-12-28",
            "y": 2282.45,
            "z": 33.55863764019858
        },
        {
            "x": "2022-12-29",
            "y": 2238.4,
            "z": 31.5648387345567
        },
        {
            "x": "2023-01-02",
            "y": 2227.67,
            "z": 30.717434556232785
        },
        {
            "x": "2023-01-03",
            "y": 2220.68,
            "z": 30.036539616189337
        },
        {
            "x": "2023-01-04",
            "y": 2257.98,
            "z": 30.35027323255528
        },
        {
            "x": "2023-01-05",
            "y": 2266.65,
            "z": 32.01325076999204
        },
        {
            "x": "2023-01-06",
            "y": 2291.97,
            "z": 34.88639231919024
        }
    ]
}