{
    "data": [
        {
            "x": "2023-05-16",
            "y": 2482.24,
            "z": 53.393496350611485
        },
        {
            "x": "2023-05-17",
            "y": 2496.66,
            "z": 52.44014403658825
        },
        {
            "x": "2023-05-18",
            "y": 2517.4,
            "z": 51.78490293672527
        },
        {
            "x": "2023-05-19",
            "y": 2539.79,
            "z": 52.66765235195144
        },
        {
            "x": "2023-05-22",
            "y": 2559.08,
            "z": 54.59361029132128
        },
        {
            "x": "2023-05-23",
            "y": 2569.55,
            "z": 57.874684386633454
        },
        {
            "x": "2023-05-24",
            "y": 2569.45,
            "z": 61.09644154776519
        },
        {
            "x": "2023-05-25",
            "y": 2556.69,
            "z": 64.05936406278589
        },
        {
            "x": "2023-05-26",
            "y": 2560.81,
            "z": 66.31845446837309
        },
        {
            "x": "2023-05-30",
            "y": 2587.52,
            "z": 67.73613976811404
        },
        {
            "x": "2023-05-31",
            "y": 2579.12,
            "z": 67.7906596368155
        },
        {
            "x": "2023-06-01",
            "y": 2571.17,
            "z": 67.23929364905206
        },
        {
            "x": "2023-06-02",
            "y": 2603.36,
            "z": 67.63610951223271
        },
        {
            "x": "2023-06-05",
            "y": 2617.41,
            "z": 67.71359533828522
        },
        {
            "x": "2023-06-07",
            "y": 2617.6,
            "z": 67.55333677908709
        },
        {
            "x": "2023-06-08",
            "y": 2612.85,
            "z": 67.71787090075676
        },
        {
            "x": "2023-06-09",
            "y": 2643.16,
            "z": 68.43314701536758
        },
        {
            "x": "2023-06-12",
            "y": 2631.35,
            "z": 67.96644474479089
        },
        {
            "x": "2023-06-13",
            "y": 2639.95,
            "z": 68.09841749639271
        },
        {
            "x": "2023-06-14",
            "y": 2621.08,
            "z": 68.46672819018272
        },
        {
            "x": "2023-06-15",
            "y": 2610.54,
            "z": 68.93168640892353
        },
        {
            "x": "2023-06-16",
            "y": 2627.79,
            "z": 69.50096159696326
        },
        {
            "x": "2023-06-19",
            "y": 2611.5,
            "z": 70.2395920623896
        },
        {
            "x": "2023-06-20",
            "y": 2606.91,
            "z": 70.02868150808044
        },
        {
            "x": "2023-06-21",
            "y": 2584.63,
            "z": 68.8555098431372
        },
        {
            "x": "2023-06-22",
            "y": 2595.7,
            "z": 67.77381689699622
        },
        {
            "x": "2023-06-23",
            "y": 2572.1,
            "z": 65.93226879536027
        },
        {
            "x": "2023-06-26",
            "y": 2584.2,
            "z": 64.37367437689234
        },
        {
            "x": "2023-06-27",
            "y": 2583.39,
            "z": 63.23322554782841
        },
        {
            "x": "2023-06-28",
            "y": 2566.19,
            "z": 62.62379527085234
        },
        {
            "x": "2023-06-29",
            "y": 2552.02,
            "z": 61.75770936814911
        },
        {
            "x": "2023-06-30",
            "y": 2566.28,
            "z": 61.335235130642864
        },
        {
            "x": "2023-07-03",
            "y": 2604.47,
            "z": 60.48085054552504
        },
        {
            "x": "2023-07-04",
            "y": 2595.31,
            "z": 59.672696728186544
        },
        {
            "x": "2023-07-05",
            "y": 2581.0,
            "z": 58.83465459440299
        },
        {
            "x": "2023-07-06",
            "y": 2558.29,
            "z": 57.49094862866856
        },
        {
            "x": "2023-07-07",
            "y": 2528.71,
            "z": 54.748390588440316
        },
        {
            "x": "2023-07-10",
            "y": 2522.7,
            "z": 51.77999807499151
        },
        {
            "x": "2023-07-11",
            "y": 2564.49,
            "z": 49.678927254707375
        },
        {
            "x": "2023-07-12",
            "y": 2576.72,
            "z": 48.17655618463401
        },
        {
            "x": "2023-07-13",
            "y": 2593.23,
            "z": 47.87216281600593
        },
        {
            "x": "2023-07-14",
            "y": 2630.3,
            "z": 48.93890758042265
        },
        {
            "x": "2023-07-17",
            "y": 2621.0,
            "z": 50.80530200054212
        },
        {
            "x": "2023-07-18",
            "y": 2609.62,
            "z": 52.11491018293445
        },
        {
            "x": "2023-07-19",
            "y": 2610.24,
            "z": 53.36785034557006
        },
        {
            "x": "2023-07-20",
            "y": 2602.23,
            "z": 54.31616124575669
        },
        {
            "x": "2023-07-21",
            "y": 2611.76,
            "z": 55.60540690254093
        },
        {
            "x": "2023-07-24",
            "y": 2630.53,
            "z": 56.058572934716196
        },
        {
            "x": "2023-07-25",
            "y": 2638.46,
            "z": 56.24550144031785
        },
        {
            "x": "2023-07-26",
            "y": 2594.36,
            "z": 55.665617646927195
        },
        {
            "x": "2023-07-27",
            "y": 2605.81,
            "z": 55.37002543091296
        },
        {
            "x": "2023-07-28",
            "y": 2610.32,
            "z": 54.34515172533132
        },
        {
            "x": "2023-07-31",
            "y": 2634.58,
            "z": 54.332480425221675
        },
        {
            "x": "2023-08-01",
            "y": 2669.07,
            "z": 55.37728903325775
        },
        {
            "x": "2023-08-02",
            "y": 2618.47,
            "z": 55.94585807516886
        },
        {
            "x": "2023-08-03",
            "y": 2607.39,
            "z": 56.318428592255714
        },
        {
            "x": "2023-08-04",
            "y": 2604.8,
            "z": 57.35547927690574
        },
        {
            "x": "2023-08-07",
            "y": 2582.71,
            "z": 57.298872244566084
        },
        {
            "x": "2023-08-08",
            "y": 2575.98,
            "z": 55.58128216690157
        },
        {
            "x": "2023-08-09",
            "y": 2607.12,
            "z": 55.789235710710685
        },
        {
            "x": "2023-08-10",
            "y": 2603.56,
            "z": 55.738445443378076
        },
        {
            "x": "2023-08-11",
            "y": 2593.26,
            "z": 55.14534674346307
        },
        {
            "x": "2023-08-14",
            "y": 2572.87,
            "z": 54.834062360968474
        },
        {
            "x": "2023-08-16",
            "y": 2527.64,
            "z": 54.37064633742841
        },
        {
            "x": "2023-08-17",
            "y": 2521.85,
            "z": 52.669021953515426
        },
        {
            "x": "2023-08-18",
            "y": 2506.5,
            "z": 50.79232121453343
        },
        {
            "x": "2023-08-21",
            "y": 2510.8,
            "z": 49.74056060921621
        },
        {
            "x": "2023-08-22",
            "y": 2517.74,
            "z": 48.827791558443515
        },
        {
            "x": "2023-08-23",
            "y": 2507.5,
            "z": 48.95679034267458
        },
        {
            "x": "2023-08-24",
            "y": 2539.68,
            "z": 49.387403039373964
        },
        {
            "x": "2023-08-25",
            "y": 2521.14,
            "z": 49.12430268550218
        },
        {
            "x": "2023-08-28",
            "y": 2545.41,
            "z": 48.3616363068791
        },
        {
            "x": "2023-08-29",
            "y": 2554.16,
            "z": 47.790707127358836
        },
        {
            "x": "2023-08-30",
            "y": 2563.22,
            "z": 46.816638623858225
        },
        {
            "x": "2023-08-31",
            "y": 2558.27,
            "z": 46.86669882467552
        },
        {
            "x": "2023-09-01",
            "y": 2565.71,
            "z": 47.870442586359665
        },
        {
            "x": "2023-09-04",
            "y": 2586.55,
            "z": 49.25373920440914
        },
        {
            "x": "2023-09-05",
            "y": 2584.18,
            "z": 51.253896883784286
        },
        {
            "x": "2023-09-06",
            "y": 2565.34,
            "z": 53.24147169823518
        },
        {
            "x": "2023-09-07",
            "y": 2550.26,
            "z": 53.54224955332735
        },
        {
            "x": "2023-09-08",
            "y": 2549.68,
            "z": 54.14780004349865
        },
        {
            "x": "2023-09-11",
            "y": 2558.88,
            "z": 54.672033109657626
        },
        {
            "x": "2023-09-12",
            "y": 2538.58,
            "z": 54.626474914190226
        },
        {
            "x": "2023-09-13",
            "y": 2536.7,
            "z": 55.23838437826915
        },
        {
            "x": "2023-09-14",
            "y": 2574.89,
            "z": 57.24643912782028
        },
        {
            "x": "2023-09-15",
            "y": 2603.28,
            "z": 59.287720458321964
        },
        {
            "x": "2023-09-18",
            "y": 2576.72,
            "z": 59.73252423166609
        },
        {
            "x": "2023-09-19",
            "y": 2561.21,
            "z": 59.52074247932883
        },
        {
            "x": "2023-09-20",
            "y": 2561.74,
            "z": 58.47692841251588
        },
        {
            "x": "2023-09-21",
            "y": 2516.97,
            "z": 56.10994450865136
        },
        {
            "x": "2023-09-22",
            "y": 2510.13,
            "z": 53.262130020204225
        },
        {
            "x": "2023-09-25",
            "y": 2497.76,
            "z": 51.601302203584076
        },
        {
            "x": "2023-09-26",
            "y": 2464.97,
            "z": 49.52055396408392
        },
        {
            "x": "2023-09-27",
            "y": 2467.07,
            "z": 47.665646424488166
        },
        {
            "x": "2023-10-04",
            "y": 2407.69,
            "z": 44.22203190338142
        },
        {
            "x": "2023-10-05",
            "y": 2405.6,
            "z": 41.07034919023924
        },
        {
            "x": "2023-10-06",
            "y": 2410.73,
            "z": 37.62454857689804
        },
        {
            "x": "2023-10-10",
            "y": 2404.58,
            "z": 35.13100659458617
        },
        {
            "x": "2023-10-11",
            "y": 2452.08,
            "z": 34.37954938986686
        },
        {
            "x": "2023-10-12",
            "y": 2481.82,
            "z": 36.89272384068225
        },
        {
            "x": "2023-10-13",
            "y": 2458.15,
            "z": 38.78868597087491
        },
        {
            "x": "2023-10-16",
            "y": 2438.24,
            "z": 40.31367047385763
        },
        {
            "x": "2023-10-17",
            "y": 2462.17,
            "z": 42.30212502148112
        },
        {
            "x": "2023-10-18",
            "y": 2464.6,
            "z": 42.01697650130664
        },
        {
            "x": "2023-10-19",
            "y": 2417.8,
            "z": 38.42021178337798
        },
        {
            "x": "2023-10-20",
            "y": 2377.0,
            "z": 34.09462023546844
        },
        {
            "x": "2023-10-23",
            "y": 2359.02,
            "z": 30.524167510851623
        },
        {
            "x": "2023-10-24",
            "y": 2385.51,
            "z": 27.497929217824726
        },
        {
            "x": "2023-10-25",
            "y": 2365.17,
            "z": 25.811629088255557
        },
        {
            "x": "2023-10-26",
            "y": 2301.08,
            "z": 25.27687609000921
        },
        {
            "x": "2023-10-27",
            "y": 2304.81,
            "z": 26.850175107507148
        },
        {
            "x": "2023-10-30",
            "y": 2312.55,
            "z": 28.97343032490853
        },
        {
            "x": "2023-10-31",
            "y": 2279.99,
            "z": 29.59996936861959
        },
        {
            "x": "2023-11-01",
            "y": 2303.56,
            "z": 30.900446264328867
        },
        {
            "x": "2023-11-02",
            "y": 2345.12,
            "z": 35.06004974166105
        },
        {
            "x": "2023-11-03",
            "y": 2370.34,
            "z": 39.001508284384
        },
        {
            "x": "2023-11-06",
            "y": 2504.37,
            "z": 44.18948394020498
        },
        {
            "x": "2023-11-07",
            "y": 2445.96,
            "z": 48.78351388012668
        },
        {
            "x": "2023-11-08",
            "y": 2423.62,
            "z": 51.19322071593374
        },
        {
            "x": "2023-11-09",
            "y": 2429.08,
            "z": 52.58585420978581
        },
        {
            "x": "2023-11-10",
            "y": 2411.66,
            "z": 53.23258060498358
        },
        {
            "x": "2023-11-13",
            "y": 2405.76,
            "z": 51.10620659327021
        },
        {
            "x": "2023-11-14",
            "y": 2435.25,
            "z": 50.64775262939711
        },
        {
            "x": "2023-11-15",
            "y": 2488.67,
            "z": 52.527647916837665
        },
        {
            "x": "2023-11-16",
            "y": 2490.18,
            "z": 54.77845672808392
        },
        {
            "x": "2023-11-17",
            "y": 2471.85,
            "z": 57.67512988839326
        },
        {
            "x": "2023-11-20",
            "y": 2493.2,
            "z": 61.842280691339525
        },
        {
            "x": "2023-11-21",
            "y": 2512.42,
            "z": 65.47795569297895
        },
        {
            "x": "2023-11-22",
            "y": 2513.7,
            "z": 68.31219610295904
        },
        {
            "x": "2023-11-23",
            "y": 2516.96,
            "z": 70.56780464374278
        },
        {
            "x": "2023-11-24",
            "y": 2498.63,
            "z": 71.8038303714605
        },
        {
            "x": "2023-11-27",
            "y": 2497.66,
            "z": 72.84436359117319
        },
        {
            "x": "2023-11-28",
            "y": 2523.76,
            "z": 73.99849163680389
        },
        {
            "x": "2023-11-29",
            "y": 2521.81,
            "z": 73.96184718761766
        },
        {
            "x": "2023-11-30",
            "y": 2537.29,
            "z": 73.38731416840434
        },
        {
            "x": "2023-12-01",
            "y": 2507.01,
            "z": 72.31442867562258
        },
        {
            "x": "2023-12-04",
            "y": 2516.95,
            "z": 70.38693858043546
        },
        {
            "x": "2023-12-05",
            "y": 2496.28,
            "z": 68.68984801379484
        },
        {
            "x": "2023-12-06",
            "y": 2497.38,
            "z": 67.94879975015893
        },
        {
            "x": "2023-12-07",
            "y": 2494.07,
            "z": 66.10249445250147
        },
        {
            "x": "2023-12-08",
            "y": 2519.85,
            "z": 66.37202893058054
        },
        {
            "x": "2023-12-11",
            "y": 2527.36,
            "z": 66.95262118294191
        },
        {
            "x": "2023-12-12",
            "y": 2537.27,
            "z": 66.55465867507797
        },
        {
            "x": "2023-12-13",
            "y": 2512.66,
            "z": 64.41762802642067
        },
        {
            "x": "2023-12-14",
            "y": 2546.18,
            "z": 64.25974344607616
        },
        {
            "x": "2023-12-15",
            "y": 2565.56,
            "z": 63.14919935214082
        },
        {
            "x": "2023-12-18",
            "y": 2568.86,
            "z": 62.271883593040215
        },
        {
            "x": "2023-12-19",
            "y": 2570.55,
            "z": 62.028194375419844
        },
        {
            "x": "2023-12-20",
            "y": 2616.3,
            "z": 63.556001027801834
        },
        {
            "x": "2023-12-21",
            "y": 2602.02,
            "z": 63.843883816808365
        }
    ]
}